streaming_json_parser/__init__.py
streaming_json_parser/iterative_state_machine.py
streaming_json_parser/streaming_json_parser.py
streaming_json_parser-0.1.0.dist-info/licenses/LICENSE
streaming_json_parser-0.1.0.dist-info/METADATA
streaming_json_parser-0.1.0.dist-info/WHEEL
streaming_json_parser-0.1.0.dist-info/top_level.txt
streaming_json_parser-0.1.0.dist-info/RECORD
