Metadata-Version: 2.4
Name: streaming-json-parser
Version: 0.1.0
Summary: A streaming JSON parser that processes JSON data incrementally, handling partial states. Useful for incrementally parsing partial responses from streaming outputs of Large Language Models (LLMs).
Author-email: Aramis Facchinetti <aramis.facchinetti16@gmail.com>
License: MIT
Project-URL: Homepage, https://github.com/aramisfacchinetti/streaming-json-parser
Project-URL: Repository, https://github.com/aramisfacchinetti/streaming-json-parser
Keywords: streaming,json,parser,llm,large language model,incremental parsing
Classifier: Programming Language :: Python :: 3
Classifier: Programming Language :: Python :: 3.8
Classifier: Programming Language :: Python :: 3.9
Classifier: Programming Language :: Python :: 3.10
Classifier: Programming Language :: Python :: 3.11
Classifier: Programming Language :: Python :: 3.12
Classifier: License :: OSI Approved :: MIT License
Classifier: Operating System :: OS Independent
Classifier: Development Status :: 5 - Production/Stable
Classifier: Intended Audience :: Developers
Classifier: Topic :: Software Development :: Libraries :: Python Modules
Classifier: Topic :: Text Processing
Requires-Python: >=3.8
License-File: LICENSE
Provides-Extra: test
Requires-Dist: pytest>=8.3.5; extra == "test"
Dynamic: license-file
